AlphaAffixedNumericType/AlphaAffixedNumericType.py
AlphaAffixedNumericType/__init__.py
AlphaAffixedNumericType/exceptions/__init__.py
AlphaAffixedNumericType-0.1.0.dist-info/LICENSE
AlphaAffixedNumericType-0.1.0.dist-info/METADATA
AlphaAffixedNumericType-0.1.0.dist-info/WHEEL
AlphaAffixedNumericType-0.1.0.dist-info/top_level.txt
AlphaAffixedNumericType-0.1.0.dist-info/RECORD
