Metadata-Version: 2.1
Name: AlphaAffixedNumericType
Version: 0.1.0
Summary: A package that provides alpha-affixed numeric type
Home-page: https://github.com/majiasheng/AlphaAffixedNumericType
Author: majiasheng
Author-email: majs.dev@gmail.com
License: UNKNOWN
Platform: UNKNOWN
Classifier: Programming Language :: Python :: 3
Classifier: License :: OSI Approved :: MIT License
Classifier: Operating System :: OS Independent
Requires-Python: >=3.6
